llama_index/storage/chat_store/azurecosmosmongovcore/__init__.py
llama_index/storage/chat_store/azurecosmosmongovcore/base.py
llama_index_storage_chat_store_azurecosmosmongovcore-1.2.1.dist-info/METADATA
llama_index_storage_chat_store_azurecosmosmongovcore-1.2.1.dist-info/WHEEL
llama_index_storage_chat_store_azurecosmosmongovcore-1.2.1.dist-info/licenses/LICENSE
llama_index_storage_chat_store_azurecosmosmongovcore-1.2.1.dist-info/RECORD
