Metadata-Version: 2.4
Name: llama-index-storage-chat-store-azurecosmosmongovcore
Version: 1.2.1
Summary: llama-index storage-chat-store azure cosmosdb mongo vcore integration
Author-email: Aayush Kataria <aayushkataria3011@gmail.com>
License-Expression: MIT
License-File: LICENSE
Requires-Python: <4.0,>=3.9
Requires-Dist: llama-index-core<0.15,>=0.13.0
Requires-Dist: pymongo<5,>=4.9.1
